knightauth/__init__.py
knightauth/admin.py
knightauth/api.py
knightauth/apps.py
knightauth/auth.py
knightauth/crypto.py
knightauth/models.py
knightauth/schemas.py
knightauth/settings.py
knightauth/signals.py
knightauth/migrations/0001_initial.py
knightauth/migrations/__init__.py
tests/__init__.py
tests/test_token_auth.py
knight_auth-0.3.0.dist-info/METADATA
knight_auth-0.3.0.dist-info/WHEEL
knight_auth-0.3.0.dist-info/top_level.txt
knight_auth-0.3.0.dist-info/RECORD
