Metadata-Version: 2.1
Name: knight-auth
Version: 0.3.0
Summary: Authentication for django-ninja, KNOX inspired
Home-page: https://github.com/knightSarai/knight-auth
Author: knightSarai
Author-email: knight.sarai.dev@gmail.com
License: MIT
Classifier: License :: OSI Approved :: MIT License
Classifier: Programming Language :: Python :: 3.11
Classifier: Framework :: Django
Classifier: Framework :: Django :: 4.0
Classifier: Intended Audience :: Developers
Requires-Python: >=3.11.0
Requires-Dist: django >=4.2.4
Requires-Dist: django-ninja >=1.0
Provides-Extra: dev
Requires-Dist: twine >=4.0.2 ; extra == 'dev'
Requires-Dist: pytest-django >=4.5.2 ; extra == 'dev'
